easy_kit/__init__.py
easy_kit/event.py
easy_kit/helper.py
easy_kit/measure.py
easy_kit/my_model.py
easy_kit/timing.py
easy_kit-0.1.25.dist-info/LICENSE
easy_kit-0.1.25.dist-info/METADATA
easy_kit-0.1.25.dist-info/WHEEL
easy_kit-0.1.25.dist-info/RECORD
